minder_downloader/__init__.py
minder_downloader/__version__.py
minder_downloader/config.py
minder_downloader/download.py
minder_downloader/info.py
minder_downloader/update.py
minder_downloader/upload.py
minder_downloader/utils.py
minder_downloader-0.1.20.dist-info/WHEEL
minder_downloader-0.1.20.dist-info/METADATA
minder_downloader-0.1.20.dist-info/RECORD
