Metadata-Version: 2.1
Name: minder-downloader
Version: 0.1.20
Summary: The minder-downloader module provides a simple interface for downloading datasets and uploading reports using the Minder research portal.
Author: Dr Eyal Soreq
Author-email: eyal.soreq@ukdri.ac.uk
Requires-Python: >3.9
Classifier: Programming Language :: Python :: 3
Classifier: Programming Language :: Python :: 3.10
Classifier: Programming Language :: Python :: 3.11
Requires-Dist: numpy (>1.24)
Requires-Dist: pandas (>2.0)
Requires-Dist: pyyaml (>6.0)
Requires-Dist: requests (>2.28.2)
Requires-Dist: tqdm (>4.65.0)
